chatcli/__init__.py
chatcli/client.py
chatcli/server.py
chatcli/modules/__init__.py
chatcli/modules/chat_protocol.py
chatcli/modules/connection_handler.py
talkiecli-0.1.4.dist-info/licenses/LICENSE
talkiecli-0.1.4.dist-info/METADATA
talkiecli-0.1.4.dist-info/WHEEL
talkiecli-0.1.4.dist-info/entry_points.txt
talkiecli-0.1.4.dist-info/top_level.txt
talkiecli-0.1.4.dist-info/RECORD
