Metadata-Version: 2.4
Name: talkieCLI
Version: 0.1.4
Summary: A command-line collaborative chat and live code editing tool
Author-email: Aswin Ganga <aswinganga.greenink@gmail.com>
License-Expression: MIT
Project-URL: Homepage, https://github.com/aswinganga-greenink/ChatCLI
Project-URL: Repository, https://github.com/aswinganga-greenink/ChatCLI
Requires-Python: >=3.10
License-File: LICENSE
Requires-Dist: asyncio
Dynamic: license-file
